valleydeight/__init__.py
valleydeight/base.py
valleydeight/choice_types.py
valleydeight/dict_types.py
valleydeight/exceptions.py
valleydeight/list_types.py
valleydeight/object_types.py
valleydeight/simple_types.py
valleydeight-0.0.4.dist-info/LICENSE
valleydeight-0.0.4.dist-info/METADATA
valleydeight-0.0.4.dist-info/WHEEL
valleydeight-0.0.4.dist-info/top_level.txt
valleydeight-0.0.4.dist-info/RECORD
