Metadata-Version: 2.1
Name: valleydeight
Version: 0.0.4
Summary: Effective dictionary and nested object validation
Home-page: https://github.com/benkrikler/valleydeight
Author: Ben Krikler
Author-email: b.krikler@gmail.com
License: UNKNOWN
Platform: UNKNOWN
Classifier: Programming Language :: Python :: 2
Classifier: Programming Language :: Python :: 3
Classifier: License :: OSI Approved :: MIT License
Classifier: Operating System :: OS Independent
Classifier: Topic :: Software Development :: Libraries :: Python Modules
Classifier: Topic :: Utilities
Classifier: Development Status :: 3 - Alpha
Requires-Dist: six
Requires-Dist: pyyaml
